ddm/__init__.py
ddm/baidu.so
ddm/common.py
ddm/config.so
ddm/iflytek.py
ddm/ownthink.py
ddm-0.0.1.dist-info/LICENSE.txt
ddm-0.0.1.dist-info/METADATA
ddm-0.0.1.dist-info/WHEEL
ddm-0.0.1.dist-info/top_level.txt
ddm-0.0.1.dist-info/RECORD
